LICENSE
MANIFEST.in
README
chiki_jinja.py
setup.py
chiki_jinja.egg-info/PKG-INFO
chiki_jinja.egg-info/SOURCES.txt
chiki_jinja.egg-info/dependency_links.txt
chiki_jinja.egg-info/not-zip-safe
chiki_jinja.egg-info/requires.txt
chiki_jinja.egg-info/top_level.txt