Metadata-Version: 1.0
Name: chiki-jinja
Version: 0.0.1
Summary: chiki jinja libs.
Home-page: https://github.com/endsh/chiki-jinja
Author: Linshao
Author-email: 438985635@qq.com
License: UNKNOWN
Platform: any
